[
    {
        "code": "BOTTLES_USED_TODAY",
        "message": "Garrafas ",
        "module": "hcm-dashboard",
        "locale": "pt_MZ"
    },
    {
        "code": "DSS_HEALTH_NATIONAL_BED_NETS_DISTRIBUTED_TODAY",
        "message": "Total de mosquiteiros distribuídos hoje",
        "module": "hcm-dashboard",
        "locale": "pt_MZ"
    },
    {
        "code": "DSS_HEALTH_NATIONAL_BED_NET_DISTRIBUTED_TODAY",
        "message": "Total de mosquiteiros distribuídos hoje",
        "module": "hcm-dashboard",
        "locale": "pt_MZ"
    },
    {
        "code": "DSS_HEALTH_NATIONAL_POPULATION_COVERED_TODAY",
        "message": "População coberta hoje",
        "module": "hcm-dashboard",
        "locale": "pt_MZ"
    },
    {
        "code": "DSS_HEALTH_NATIONAL_TOTAL_POPULATION_COVERED",
        "message": "População total coberta",
        "module": "hcm-dashboard",
        "locale": "pt_MZ"
    },
    {
        "code": "DSS_LAST_SYNC_TIME",
        "message": "Hora da última sincronização",
        "module": "hcm-dashboard",
        "locale": "pt_MZ"
    },
    {
        "code": "DSS_NETWORK_FAILURE_ERROR",
        "message": "Erro de rede!!! Conecte-se à Internet para atualizar o painel",
        "module": "hcm-dashboard",
        "locale": "pt_MZ"
    },
    {
        "code": "DSS_NOTE_DESCRIPTION",
        "message": "Role a barra para a direita para ver todos os detalhes de um trabalhador\n\nÍndice de cobertura de casas = Total de casas pulverizadas / Total de casas visitadas\n\nRácio de cobertura de quartos = Total de quartos pulverizados / Total de quartos disponíveis",
        "module": "hcm-dashboard",
        "locale": "pt_MZ"
    },
    {
        "code": "DSS_NOTE_TITLE",
        "message": "Observação:",
        "module": "hcm-dashboard",
        "locale": "pt_MZ"
    },
    {
        "code": "DSS_NO_OF_BOTTLES_USED_TODAY",
        "message": "Nº de garrafas usadas hoje",
        "module": "hcm-dashboard",
        "locale": "pt_MZ"
    },
    {
        "code": "DSS_NO_OF_HOUSES_NOT_SPRAYED_TODAY",
        "message": "Nº de casas não pulverizadas hoje",
        "module": "hcm-dashboard",
        "locale": "pt_MZ"
    },
    {
        "code": "DSS_NO_OF_HOUSES_SPRAYED_TODAY",
        "message": "Nº de casas pulverizadas hoje",
        "module": "hcm-dashboard",
        "locale": "pt_MZ"
    },
    {
        "code": "DSS_NO_OF_HOUSES_VISITED_TODAY",
        "message": "Nº de casas visitadas hoje",
        "module": "hcm-dashboard",
        "locale": "pt_MZ"
    },
    {
        "code": "DSS_PERCENT_TARGET_ACHIEVEMENT_TODAY",
        "message": "% da meta alcançada hoje",
        "module": "hcm-dashboard",
        "locale": "pt_MZ"
    },
    {
        "code": "DSS_REMAINING_BOTTLES",
        "message": "Garrafas restantes",
        "module": "hcm-dashboard",
        "locale": "pt_MZ"
    },
    {
        "code": "DSS_SOME_ERROR_OCCURED",
        "message": "Ocorreu algum erro",
        "module": "hcm-dashboard",
        "locale": "pt_MZ"
    },
    {
        "code": "DSS_TOTAL_BOTTLES_USED",
        "message": "Total de garrafas usadas hoje",
        "module": "hcm-dashboard",
        "locale": "pt_MZ"
    },
    {
        "code": "DSS_TOTAL_HOUSEHOLD_SPRAYED",
        "message": "Total de famílias pulverizadas hoje",
        "module": "hcm-dashboard",
        "locale": "pt_MZ"
    },
    {
        "code": "DSS_USER_ID_NAME",
        "message": "ID/Nome do usuário",
        "module": "hcm-dashboard",
        "locale": "pt_MZ"
    },
    {
        "code": "HOME_DASHBOARD_LABEL",
        "message": "Painel",
        "module": "hcm-dashboard",
        "locale": "pt_MZ"
    },
    {
        "code": "HOUSEHOLDS_SPRAYED",
        "message": "Famílias pulverizadas",
        "module": "hcm-dashboard",
        "locale": "pt_MZ"
    },
    {
        "code": "HOUSEHOLDS_VISITED",
        "message": "Domicílios visitados",
        "module": "hcm-dashboard",
        "locale": "pt_MZ"
    },
    {
        "code": "HOUSEHOLD_COVERAGE",
        "message": "Cobertura doméstica",
        "module": "hcm-dashboard",
        "locale": "pt_MZ"
    },
    {
        "code": "NO._OF_HOUSES_NOT_SPRAYE",
        "message": "Nº de casas não pulverizadas",
        "module": "hcm-dashboard",
        "locale": "pt_MZ"
    },
    {
        "code": "NO._OF_HOUSES_NOT_SPRAYED_TODAY",
        "message": "Nº de casas não pulverizadas hoje",
        "module": "hcm-dashboard",
        "locale": "pt_MZ"
    },
    {
        "code": "NO._OF_REMAINING_BOTTLES",
        "message": "Nº de garrafas restantes",
        "module": "hcm-dashboard",
        "locale": "pt_MZ"
    },
    {
        "code": "PERCENTAGE_VALUE",
        "message": "Porcentagem %",
        "module": "hcm-dashboard",
        "locale": "pt_MZ"
    },
    {
        "code": "POPULATION_COVERAGE",
        "message": "Cobertura populacional",
        "module": "hcm-dashboard",
        "locale": "pt_MZ"
    },
    {
        "code": "PROVINCE",
        "message": "Província",
        "module": "hcm-dashboard",
        "locale": "pt_MZ"
    },
    {
        "code": "PROVINCES",
        "message": "Províncias",
        "module": "hcm-dashboard",
        "locale": "pt_MZ"
    },
    {
        "code": "QUANTITY",
        "message": "Quantidade",
        "module": "hcm-dashboard",
        "locale": "pt_MZ"
    },
    {
        "code": "STOCK_COUNT_PER_USER",
        "message": "Contagem de estoque por usuário",
        "module": "hcm-dashboard",
        "locale": "pt_MZ"
    },
    {
        "code": "TOTAL_COUNT",
        "message": "Contagem total",
        "module": "hcm-dashboard",
        "locale": "pt_MZ"
    },
    {
        "code": "TOTAL_HOUSEHOLDS_VISITED_CUMULATIVE",
        "message": "Nº do total de casas",
        "module": "hcm-dashboard",
        "locale": "pt_MZ"
    },
    {
        "code": "TOTAL_HOUSEHOLDS_VISITED_TODAY",
        "message": "Nº de casas visitadas hoje",
        "module": "hcm-dashboard",
        "locale": "pt_MZ"
    },
    {
        "code": "USERNAME",
        "message": "Nome de usuário",
        "module": "hcm-dashboard",
        "locale": "pt_MZ"
    }
]